counter/counter.vhd
library ieee;
use ieee.std_logic_1164.all;
use ieee.numeric_std.all;

entity counter is
  generic (
    data_width : integer := 8
  );
  port (
    reset : in std_logic;
    clock : in std_logic;
    count : out std_logic_vector(data_width-1 downto 0)
  );
end entity;
architecture behavioral of counter is
  signal count_reg : unsigned(data_width-1 downto 0) := (others => '0');
begin
  process (clock, reset)
  begin
    if rising_edge(clock) then
      count_reg <= count_reg + 1;
    end if;
    if reset = '1' then
      count_reg <= (others => '0');
    end if;
  end process;
  count <= std_logic_vector(count_reg);
end architecture;

timer/timer.vhd
library ieee;
use ieee.std_logic_1164.all;
use ieee.numeric_std.all;

entity timer is
  generic (
    duration_sec : integer;
    frequency_hz : integer
  );
  port (
    reset : in std_logic;
    clock : in std_logic;
    start : in std_logic;
    ended : out std_logic
  );
end entity;
architecture behavioral of timer is
  constant required_width : integer := 32;

  component counter is
    generic (
      data_width : integer := 8
    );
    port (
      reset : in std_logic;
      clock : in std_logic;
      count : out std_logic_vector(data_width-1 downto 0)
    );
  end component;

  signal anded_clock : std_logic := '0';
  signal running     : std_logic := '0';
  signal count_reg   : std_logic_vector(required_width-1 downto 0) := (others => '0');
begin
  running_latch : process (start, reset)
  begin
    if rising_edge(start) then
      running <= '1';
    end if;
    if reset = '1'   then
      running <= '0';
    end if;
  end process;

  anded_clock <= clock and running;
  ended       <= '1' when unsigned(count_reg) > (duration_sec*frequency_hz) else '0';
  
  counter_instance : counter
    generic map (required_width)
    port map (reset, anded_clock, count_reg);
end architecture;

timer/tb.vhd
library ieee;
use ieee.std_logic_1164.all;
use ieee.numeric_std.all;

entity tb is
end tb;

architecture test of tb is
  constant frq : real      := 10.0;
  signal   run : boolean   := true;
  signal   rst : std_logic := '0';
  signal   clk : std_logic := '0';

  component timer is
    generic (
      duration_sec : integer;
      frequency_hz : integer
    );
    port (
      reset : in std_logic;
      clock : in std_logic;
      start : in std_logic;
      ended : out std_logic
    );
  end component;

  signal start_input  : std_logic := '0';
  signal ended_output : std_logic;
begin
  run <= false after 100 sec;
  clk <= not clk after (0.5/frq) * 1 sec when run;
  rst <= '1' after 55 sec, '0' after 56 sec;

  start_input <= '1' after 20 sec, '0' after 20.00001 sec,
                 '1' after 60 sec, '0' after 61 sec;

  timer_instance : timer
    generic map (30, integer(frq))
    port map(rst, clk, start_input, ended_output);
end test;

timer/build/timer.vcd
$date
  Tue Feb 04 21:19:27 2025
$end
$version
  GHDL v0
$end
$timescale
  1 fs
$end
$scope module standard $end
$upscope $end
$scope module std_logic_1164 $end
$upscope $end
$scope module numeric_std $end
$upscope $end
$scope module tb $end
$var reg 1 ! run $end
$var reg 1 " rst $end
$var reg 1 # clk $end
$var reg 1 $ start_input $end
$var reg 1 % ended_output $end
$scope module timer_instance $end
$var reg 1 & reset $end
$var reg 1 ' clock $end
$var reg 1 ( start $end
$var reg 1 ) ended $end
$var reg 1 * anded_clock $end
$var reg 1 + running $end
$var reg 32 , count_reg[31:0] $end
$scope module counter_instance $end
$var reg 1 - reset $end
$var reg 1 . clock $end
$var reg 32 / count[31:0] $end
$var reg 32 0 count_reg[31:0] $end
$upscope $end
$upscope $end
$upscope $end
$enddefinitions $end
#0
1!
0"
0#
0$
0%
0&
0'
0(
0)
0*
0+
b00000000000000000000000000000000 ,
0-
0.
b00000000000000000000000000000000 /
b00000000000000000000000000000000 0
#50000000000000
1#
1'
#100000000000000
0#
0'
#150000000000000
1#
1'
#200000000000000
0#
0'
#250000000000000
1#
1'
#300000000000000
0#
0'
#350000000000000
1#
1'
#400000000000000
0#
0'
#450000000000000
1#
1'
#500000000000000
0#
0'
#550000000000000
1#
1'
#600000000000000
0#
0'
#650000000000000
1#
1'
#700000000000000
0#
0'
#750000000000000
1#
1'
#800000000000000
0#
0'
#850000000000000
1#
1'
#900000000000000
0#
0'
#950000000000000
1#
1'
#1000000000000000
0#
0'
#1050000000000000
1#
1'
#1100000000000000
0#
0'
#1150000000000000
1#
1'
#1200000000000000
0#
0'
#1250000000000000
1#
1'
#1300000000000000
0#
0'
#1350000000000000
1#
1'
#1400000000000000
0#
0'
#1450000000000000
1#
1'
#1500000000000000
0#
0'
#1550000000000000
1#
1'
#1600000000000000
0#
0'
#1650000000000000
1#
1'
#1700000000000000
0#
0'
#1750000000000000
1#
1'
#1800000000000000
0#
0'
#1850000000000000
1#
1'
#1900000000000000
0#
0'
#1950000000000000
1#
1'
#2000000000000000
0#
0'
#2050000000000000
1#
1'
#2100000000000000
0#
0'
#2150000000000000
1#
1'
#2200000000000000
0#
0'
#2250000000000000
1#
1'
#2300000000000000
0#
0'
#2350000000000000
1#
1'
#2400000000000000
0#
0'
#2450000000000000
1#
1'
#2500000000000000
0#
0'
#2550000000000000
1#
1'
#2600000000000000
0#
0'
#2650000000000000
1#
1'
#2700000000000000
0#
0'
#2750000000000000
1#
1'
#2800000000000000
0#
0'
#2850000000000000
1#
1'
#2900000000000000
0#
0'
#2950000000000000
1#
1'
#3000000000000000
0#
0'
#3050000000000000
1#
1'
#3100000000000000
0#
0'
#3150000000000000
1#
1'
#3200000000000000
0#
0'
#3250000000000000
1#
1'
#3300000000000000
0#
0'
#3350000000000000
1#
1'
#3400000000000000
0#
0'
#3450000000000000
1#
1'
#3500000000000000
0#
0'
#3550000000000000
1#
1'
#3600000000000000
0#
0'
#3650000000000000
1#
1'
#3700000000000000
0#
0'
#3750000000000000
1#
1'
#3800000000000000
0#
0'
#3850000000000000
1#
1'
#3900000000000000
0#
0'
#3950000000000000
1#
1'
#4000000000000000
0#
0'
#4050000000000000
1#
1'
#4100000000000000
0#
0'
#4150000000000000
1#
1'
#4200000000000000
0#
0'
#4250000000000000
1#
1'
#4300000000000000
0#
0'
#4350000000000000
1#
1'
#4400000000000000
0#
0'
#4450000000000000
1#
1'
#4500000000000000
0#
0'
#4550000000000000
1#
1'
#4600000000000000
0#
0'
#4650000000000000
1#
1'
#4700000000000000
0#
0'
#4750000000000000
1#
1'
#4800000000000000
0#
0'
#4850000000000000
1#
1'
#4900000000000000
0#
0'
#4950000000000000
1#
1'
#5000000000000000
0#
0'
#5050000000000000
1#
1'
#5100000000000000
0#
0'
#5150000000000000
1#
1'
#5200000000000000
0#
0'
#5250000000000000
1#
1'
#5300000000000000
0#
0'
#5350000000000000
1#
1'
#5400000000000000
0#
0'
#5450000000000000
1#
1'
#5500000000000000
0#
0'
#5550000000000000
1#
1'
#5600000000000000
0#
0'
#5650000000000000
1#
1'
#5700000000000000
0#
0'
#5750000000000000
1#
1'
#5800000000000000
0#
0'
#5850000000000000
1#
1'
#5900000000000000
0#
0'
#5950000000000000
1#
1'
#6000000000000000
0#
0'
#6050000000000000
1#
1'
#6100000000000000
0#
0'
#6150000000000000
1#
1'
#6200000000000000
0#
0'
#6250000000000000
1#
1'
#6300000000000000
0#
0'
#6350000000000000
1#
1'
#6400000000000000
0#
0'
#6450000000000000
1#
1'
#6500000000000000
0#
0'
#6550000000000000
1#
1'
#6600000000000000
0#
0'
#6650000000000000
1#
1'
#6700000000000000
0#
0'
#6750000000000000
1#
1'
#6800000000000000
0#
0'
#6850000000000000
1#
1'
#6900000000000000
0#
0'
#6950000000000000
1#
1'
#7000000000000000
0#
0'
#7050000000000000
1#
1'
#7100000000000000
0#
0'
#7150000000000000
1#
1'
#7200000000000000
0#
0'
#7250000000000000
1#
1'
#7300000000000000
0#
0'
#7350000000000000
1#
1'
#7400000000000000
0#
0'
#7450000000000000
1#
1'
#7500000000000000
0#
0'
#7550000000000000
1#
1'
#7600000000000000
0#
0'
#7650000000000000
1#
1'
#7700000000000000
0#
0'
#7750000000000000
1#
1'
#7800000000000000
0#
0'
#7850000000000000
1#
1'
#7900000000000000
0#
0'
#7950000000000000
1#
1'
#8000000000000000
0#
0'
#8050000000000000
1#
1'
#8100000000000000
0#
0'
#8150000000000000
1#
1'
#8200000000000000
0#
0'
#8250000000000000
1#
1'
#8300000000000000
0#
0'
#8350000000000000
1#
1'
#8400000000000000
0#
0'
#8450000000000000
1#
1'
#8500000000000000
0#
0'
#8550000000000000
1#
1'
#8600000000000000
0#
0'
#8650000000000000
1#
1'
#8700000000000000
0#
0'
#8750000000000000
1#
1'
#8800000000000000
0#
0'
#8850000000000000
1#
1'
#8900000000000000
0#
0'
#8950000000000000
1#
1'
#9000000000000000
0#
0'
#9050000000000000
1#
1'
#9100000000000000
0#
0'
#9150000000000000
1#
1'
#9200000000000000
0#
0'
#9250000000000000
1#
1'
#9300000000000000
0#
0'
#9350000000000000
1#
1'
#9400000000000000
0#
0'
#9450000000000000
1#
1'
#9500000000000000
0#
0'
#9550000000000000
1#
1'
#9600000000000000
0#
0'
#9650000000000000
1#
1'
#9700000000000000
0#
0'
#9750000000000000
1#
1'
#9800000000000000
0#
0'
#9850000000000000
1#
1'
#9900000000000000
0#
0'
#9950000000000000
1#
1'
#10000000000000000
0#
0'
#10050000000000000
1#
1'
#10100000000000000
0#
0'
#10150000000000000
1#
1'
#10200000000000000
0#
0'
#10250000000000000
1#
1'
#10300000000000000
0#
0'
#10350000000000000
1#
1'
#10400000000000000
0#
0'
#10450000000000000
1#
1'
#10500000000000000
0#
0'
#10550000000000000
1#
1'
#10600000000000000
0#
0'
#10650000000000000
1#
1'
#10700000000000000
0#
0'
#10750000000000000
1#
1'
#10800000000000000
0#
0'
#10850000000000000
1#
1'
#10900000000000000
0#
0'
#10950000000000000
1#
1'
#11000000000000000
0#
0'
#11050000000000000
1#
1'
#11100000000000000
0#
0'
#11150000000000000
1#
1'
#11200000000000000
0#
0'
#11250000000000000
1#
1'
#11300000000000000
0#
0'
#11350000000000000
1#
1'
#11400000000000000
0#
0'
#11450000000000000
1#
1'
#11500000000000000
0#
0'
#11550000000000000
1#
1'
#11600000000000000
0#
0'
#11650000000000000
1#
1'
#11700000000000000
0#
0'
#11750000000000000
1#
1'
#11800000000000000
0#
0'
#11850000000000000
1#
1'
#11900000000000000
0#
0'
#11950000000000000
1#
1'
#12000000000000000
0#
0'
#12050000000000000
1#
1'
#12100000000000000
0#
0'
#12150000000000000
1#
1'
#12200000000000000
0#
0'
#12250000000000000
1#
1'
#12300000000000000
0#
0'
#12350000000000000
1#
1'
#12400000000000000
0#
0'
#12450000000000000
1#
1'
#12500000000000000
0#
0'
#12550000000000000
1#
1'
#12600000000000000
0#
0'
#12650000000000000
1#
1'
#12700000000000000
0#
0'
#12750000000000000
1#
1'
#12800000000000000
0#
0'
#12850000000000000
1#
1'
#12900000000000000
0#
0'
#12950000000000000
1#
1'
#13000000000000000
0#
0'
#13050000000000000
1#
1'
#13100000000000000
0#
0'
#13150000000000000
1#
1'
#13200000000000000
0#
0'
#13250000000000000
1#
1'
#13300000000000000
0#
0'
#13350000000000000
1#
1'
#13400000000000000
0#
0'
#13450000000000000
1#
1'
#13500000000000000
0#
0'
#13550000000000000
1#
1'
#13600000000000000
0#
0'
#13650000000000000
1#
1'
#13700000000000000
0#
0'
#13750000000000000
1#
1'
#13800000000000000
0#
0'
#13850000000000000
1#
1'
#13900000000000000
0#
0'
#13950000000000000
1#
1'
#14000000000000000
0#
0'
#14050000000000000
1#
1'
#14100000000000000
0#
0'
#14150000000000000
1#
1'
#14200000000000000
0#
0'
#14250000000000000
1#
1'
#14300000000000000
0#
0'
#14350000000000000
1#
1'
#14400000000000000
0#
0'
#14450000000000000
1#
1'
#14500000000000000
0#
0'
#14550000000000000
1#
1'
#14600000000000000
0#
0'
#14650000000000000
1#
1'
#14700000000000000
0#
0'
#14750000000000000
1#
1'
#14800000000000000
0#
0'
#14850000000000000
1#
1'
#14900000000000000
0#
0'
#14950000000000000
1#
1'
#15000000000000000
0#
0'
#15050000000000000
1#
1'
#15100000000000000
0#
0'
#15150000000000000
1#
1'
#15200000000000000
0#
0'
#15250000000000000
1#
1'
#15300000000000000
0#
0'
#15350000000000000
1#
1'
#15400000000000000
0#
0'
#15450000000000000
1#
1'
#15500000000000000
0#
0'
#15550000000000000
1#
1'
#15600000000000000
0#
0'
#15650000000000000
1#
1'
#15700000000000000
0#
0'
#15750000000000000
1#
1'
#15800000000000000
0#
0'
#15850000000000000
1#
1'
#15900000000000000
0#
0'
#15950000000000000
1#
1'
#16000000000000000
0#
0'
#16050000000000000
1#
1'
#16100000000000000
0#
0'
#16150000000000000
1#
1'
#16200000000000000
0#
0'
#16250000000000000
1#
1'
#16300000000000000
0#
0'
#16350000000000000
1#
1'
#16400000000000000
0#
0'
#16450000000000000
1#
1'
#16500000000000000
0#
0'
#16550000000000000
1#
1'
#16600000000000000
0#
0'
#16650000000000000
1#
1'
#16700000000000000
0#
0'
#16750000000000000
1#
1'
#16800000000000000
0#
0'
#16850000000000000
1#
1'
#16900000000000000
0#
0'
#16950000000000000
1#
1'
#17000000000000000
0#
0'
#17050000000000000
1#
1'
#17100000000000000
0#
0'
#17150000000000000
1#
1'
#17200000000000000
0#
0'
#17250000000000000
1#
1'
#17300000000000000
0#
0'
#17350000000000000
1#
1'
#17400000000000000
0#
0'
#17450000000000000
1#
1'
#17500000000000000
0#
0'
#17550000000000000
1#
1'
#17600000000000000
0#
0'
#17650000000000000
1#
1'
#17700000000000000
0#
0'
#17750000000000000
1#
1'
#17800000000000000
0#
0'
#17850000000000000
1#
1'
#17900000000000000
0#
0'
#17950000000000000
1#
1'
#18000000000000000
0#
0'
#18050000000000000
1#
1'
#18100000000000000
0#
0'
#18150000000000000
1#
1'
#18200000000000000
0#
0'
#18250000000000000
1#
1'
#18300000000000000
0#
0'
#18350000000000000
1#
1'
#18400000000000000
0#
0'
#18450000000000000
1#
1'
#18500000000000000
0#
0'
#18550000000000000
1#
1'
#18600000000000000
0#
0'
#18650000000000000
1#
1'
#18700000000000000
0#
0'
#18750000000000000
1#
1'
#18800000000000000
0#
0'
#18850000000000000
1#
1'
#18900000000000000
0#
0'
#18950000000000000
1#
1'
#19000000000000000
0#
0'
#19050000000000000
1#
1'
#19100000000000000
0#
0'
#19150000000000000
1#
1'
#19200000000000000
0#
0'
#19250000000000000
1#
1'
#19300000000000000
0#
0'
#19350000000000000
1#
1'
#19400000000000000
0#
0'
#19450000000000000
1#
1'
#19500000000000000
0#
0'
#19550000000000000
1#
1'
#19600000000000000
0#
0'
#19650000000000000
1#
1'
#19700000000000000
0#
0'
#19750000000000000
1#
1'
#19800000000000000
0#
0'
#19850000000000000
1#
1'
#19900000000000000
0#
0'
#19950000000000000
1#
1'
#20000000000000000
0#
1$
0'
1(
1+
#20000010000000000
0$
0(
#20050000000000000
1#
1'
1*
b00000000000000000000000000000001 ,
1.
b00000000000000000000000000000001 /
b00000000000000000000000000000001 0
#20100000000000000
0#
0'
0*
0.
#20150000000000000
1#
1'
1*
b00000000000000000000000000000010 ,
1.
b00000000000000000000000000000010 /
b00000000000000000000000000000010 0
#20200000000000000
0#
0'
0*
0.
#20250000000000000
1#
1'
1*
b00000000000000000000000000000011 ,
1.
b00000000000000000000000000000011 /
b00000000000000000000000000000011 0
#20300000000000000
0#
0'
0*
0.
#20350000000000000
1#
1'
1*
b00000000000000000000000000000100 ,
1.
b00000000000000000000000000000100 /
b00000000000000000000000000000100 0
#20400000000000000
0#
0'
0*
0.
#20450000000000000
1#
1'
1*
b00000000000000000000000000000101 ,
1.
b00000000000000000000000000000101 /
b00000000000000000000000000000101 0
#20500000000000000
0#
0'
0*
0.
#20550000000000000
1#
1'
1*
b00000000000000000000000000000110 ,
1.
b00000000000000000000000000000110 /
b00000000000000000000000000000110 0
#20600000000000000
0#
0'
0*
0.
#20650000000000000
1#
1'
1*
b00000000000000000000000000000111 ,
1.
b00000000000000000000000000000111 /
b00000000000000000000000000000111 0
#20700000000000000
0#
0'
0*
0.
#20750000000000000
1#
1'
1*
b00000000000000000000000000001000 ,
1.
b00000000000000000000000000001000 /
b00000000000000000000000000001000 0
#20800000000000000
0#
0'
0*
0.
#20850000000000000
1#
1'
1*
b00000000000000000000000000001001 ,
1.
b00000000000000000000000000001001 /
b00000000000000000000000000001001 0
#20900000000000000
0#
0'
0*
0.
#20950000000000000
1#
1'
1*
b00000000000000000000000000001010 ,
1.
b00000000000000000000000000001010 /
b00000000000000000000000000001010 0
#21000000000000000
0#
0'
0*
0.
#21050000000000000
1#
1'
1*
b00000000000000000000000000001011 ,
1.
b00000000000000000000000000001011 /
b00000000000000000000000000001011 0
#21100000000000000
0#
0'
0*
0.
#21150000000000000
1#
1'
1*
b00000000000000000000000000001100 ,
1.
b00000000000000000000000000001100 /
b00000000000000000000000000001100 0
#21200000000000000
0#
0'
0*
0.
#21250000000000000
1#
1'
1*
b00000000000000000000000000001101 ,
1.
b00000000000000000000000000001101 /
b00000000000000000000000000001101 0
#21300000000000000
0#
0'
0*
0.
#21350000000000000
1#
1'
1*
b00000000000000000000000000001110 ,
1.
b00000000000000000000000000001110 /
b00000000000000000000000000001110 0
#21400000000000000
0#
0'
0*
0.
#21450000000000000
1#
1'
1*
b00000000000000000000000000001111 ,
1.
b00000000000000000000000000001111 /
b00000000000000000000000000001111 0
#21500000000000000
0#
0'
0*
0.
#21550000000000000
1#
1'
1*
b00000000000000000000000000010000 ,
1.
b00000000000000000000000000010000 /
b00000000000000000000000000010000 0
#21600000000000000
0#
0'
0*
0.
#21650000000000000
1#
1'
1*
b00000000000000000000000000010001 ,
1.
b00000000000000000000000000010001 /
b00000000000000000000000000010001 0
#21700000000000000
0#
0'
0*
0.
#21750000000000000
1#
1'
1*
b00000000000000000000000000010010 ,
1.
b00000000000000000000000000010010 /
b00000000000000000000000000010010 0
#21800000000000000
0#
0'
0*
0.
#21850000000000000
1#
1'
1*
b00000000000000000000000000010011 ,
1.
b00000000000000000000000000010011 /
b00000000000000000000000000010011 0
#21900000000000000
0#
0'
0*
0.
#21950000000000000
1#
1'
1*
b00000000000000000000000000010100 ,
1.
b00000000000000000000000000010100 /
b00000000000000000000000000010100 0
#22000000000000000
0#
0'
0*
0.
#22050000000000000
1#
1'
1*
b00000000000000000000000000010101 ,
1.
b00000000000000000000000000010101 /
b00000000000000000000000000010101 0
#22100000000000000
0#
0'
0*
0.
#22150000000000000
1#
1'
1*
b00000000000000000000000000010110 ,
1.
b00000000000000000000000000010110 /
b00000000000000000000000000010110 0
#22200000000000000
0#
0'
0*
0.
#22250000000000000
1#
1'
1*
b00000000000000000000000000010111 ,
1.
b00000000000000000000000000010111 /
b00000000000000000000000000010111 0
#22300000000000000
0#
0'
0*
0.
#22350000000000000
1#
1'
1*
b00000000000000000000000000011000 ,
1.
b00000000000000000000000000011000 /
b00000000000000000000000000011000 0
#22400000000000000
0#
0'
0*
0.
#22450000000000000
1#
1'
1*
b00000000000000000000000000011001 ,
1.
b00000000000000000000000000011001 /
b00000000000000000000000000011001 0
#22500000000000000
0#
0'
0*
0.
#22550000000000000
1#
1'
1*
b00000000000000000000000000011010 ,
1.
b00000000000000000000000000011010 /
b00000000000000000000000000011010 0
#22600000000000000
0#
0'
0*
0.
#22650000000000000
1#
1'
1*
b00000000000000000000000000011011 ,
1.
b00000000000000000000000000011011 /
b00000000000000000000000000011011 0
#22700000000000000
0#
0'
0*
0.
#22750000000000000
1#
1'
1*
b00000000000000000000000000011100 ,
1.
b00000000000000000000000000011100 /
b00000000000000000000000000011100 0
#22800000000000000
0#
0'
0*
0.
#22850000000000000
1#
1'
1*
b00000000000000000000000000011101 ,
1.
b00000000000000000000000000011101 /
b00000000000000000000000000011101 0
#22900000000000000
0#
0'
0*
0.
#22950000000000000
1#
1'
1*
b00000000000000000000000000011110 ,
1.
b00000000000000000000000000011110 /
b00000000000000000000000000011110 0
#23000000000000000
0#
0'
0*
0.
#23050000000000000
1#
1'
1*
b00000000000000000000000000011111 ,
1.
b00000000000000000000000000011111 /
b00000000000000000000000000011111 0
#23100000000000000
0#
0'
0*
0.
#23150000000000000
1#
1'
1*
b00000000000000000000000000100000 ,
1.
b00000000000000000000000000100000 /
b00000000000000000000000000100000 0
#23200000000000000
0#
0'
0*
0.
#23250000000000000
1#
1'
1*
b00000000000000000000000000100001 ,
1.
b00000000000000000000000000100001 /
b00000000000000000000000000100001 0
#23300000000000000
0#
0'
0*
0.
#23350000000000000
1#
1'
1*
b00000000000000000000000000100010 ,
1.
b00000000000000000000000000100010 /
b00000000000000000000000000100010 0
#23400000000000000
0#
0'
0*
0.
#23450000000000000
1#
1'
1*
b00000000000000000000000000100011 ,
1.
b00000000000000000000000000100011 /
b00000000000000000000000000100011 0
#23500000000000000
0#
0'
0*
0.
#23550000000000000
1#
1'
1*
b00000000000000000000000000100100 ,
1.
b00000000000000000000000000100100 /
b00000000000000000000000000100100 0
#23600000000000000
0#
0'
0*
0.
#23650000000000000
1#
1'
1*
b00000000000000000000000000100101 ,
1.
b00000000000000000000000000100101 /
b00000000000000000000000000100101 0
#23700000000000000
0#
0'
0*
0.
#23750000000000000
1#
1'
1*
b00000000000000000000000000100110 ,
1.
b00000000000000000000000000100110 /
b00000000000000000000000000100110 0
#23800000000000000
0#
0'
0*
0.
#23850000000000000
1#
1'
1*
b00000000000000000000000000100111 ,
1.
b00000000000000000000000000100111 /
b00000000000000000000000000100111 0
#23900000000000000
0#
0'
0*
0.
#23950000000000000
1#
1'
1*
b00000000000000000000000000101000 ,
1.
b00000000000000000000000000101000 /
b00000000000000000000000000101000 0
#24000000000000000
0#
0'
0*
0.
#24050000000000000
1#
1'
1*
b00000000000000000000000000101001 ,
1.
b00000000000000000000000000101001 /
b00000000000000000000000000101001 0
#24100000000000000
0#
0'
0*
0.
#24150000000000000
1#
1'
1*
b00000000000000000000000000101010 ,
1.
b00000000000000000000000000101010 /
b00000000000000000000000000101010 0
#24200000000000000
0#
0'
0*
0.
#24250000000000000
1#
1'
1*
b00000000000000000000000000101011 ,
1.
b00000000000000000000000000101011 /
b00000000000000000000000000101011 0
#24300000000000000
0#
0'
0*
0.
#24350000000000000
1#
1'
1*
b00000000000000000000000000101100 ,
1.
b00000000000000000000000000101100 /
b00000000000000000000000000101100 0
#24400000000000000
0#
0'
0*
0.
#24450000000000000
1#
1'
1*
b00000000000000000000000000101101 ,
1.
b00000000000000000000000000101101 /
b00000000000000000000000000101101 0
#24500000000000000
0#
0'
0*
0.
#24550000000000000
1#
1'
1*
b00000000000000000000000000101110 ,
1.
b00000000000000000000000000101110 /
b00000000000000000000000000101110 0
#24600000000000000
0#
0'
0*
0.
#24650000000000000
1#
1'
1*
b00000000000000000000000000101111 ,
1.
b00000000000000000000000000101111 /
b00000000000000000000000000101111 0
#24700000000000000
0#
0'
0*
0.
#24750000000000000
1#
1'
1*
b00000000000000000000000000110000 ,
1.
b00000000000000000000000000110000 /
b00000000000000000000000000110000 0
#24800000000000000
0#
0'
0*
0.
#24850000000000000
1#
1'
1*
b00000000000000000000000000110001 ,
1.
b00000000000000000000000000110001 /
b00000000000000000000000000110001 0
#24900000000000000
0#
0'
0*
0.
#24950000000000000
1#
1'
1*
b00000000000000000000000000110010 ,
1.
b00000000000000000000000000110010 /
b00000000000000000000000000110010 0
#25000000000000000
0#
0'
0*
0.
#25050000000000000
1#
1'
1*
b00000000000000000000000000110011 ,
1.
b00000000000000000000000000110011 /
b00000000000000000000000000110011 0
#25100000000000000
0#
0'
0*
0.
#25150000000000000
1#
1'
1*
b00000000000000000000000000110100 ,
1.
b00000000000000000000000000110100 /
b00000000000000000000000000110100 0
#25200000000000000
0#
0'
0*
0.
#25250000000000000
1#
1'
1*
b00000000000000000000000000110101 ,
1.
b00000000000000000000000000110101 /
b00000000000000000000000000110101 0
#25300000000000000
0#
0'
0*
0.
#25350000000000000
1#
1'
1*
b00000000000000000000000000110110 ,
1.
b00000000000000000000000000110110 /
b00000000000000000000000000110110 0
#25400000000000000
0#
0'
0*
0.
#25450000000000000
1#
1'
1*
b00000000000000000000000000110111 ,
1.
b00000000000000000000000000110111 /
b00000000000000000000000000110111 0
#25500000000000000
0#
0'
0*
0.
#25550000000000000
1#
1'
1*
b00000000000000000000000000111000 ,
1.
b00000000000000000000000000111000 /
b00000000000000000000000000111000 0
#25600000000000000
0#
0'
0*
0.
#25650000000000000
1#
1'
1*
b00000000000000000000000000111001 ,
1.
b00000000000000000000000000111001 /
b00000000000000000000000000111001 0
#25700000000000000
0#
0'
0*
0.
#25750000000000000
1#
1'
1*
b00000000000000000000000000111010 ,
1.
b00000000000000000000000000111010 /
b00000000000000000000000000111010 0
#25800000000000000
0#
0'
0*
0.
#25850000000000000
1#
1'
1*
b00000000000000000000000000111011 ,
1.
b00000000000000000000000000111011 /
b00000000000000000000000000111011 0
#25900000000000000
0#
0'
0*
0.
#25950000000000000
1#
1'
1*
b00000000000000000000000000111100 ,
1.
b00000000000000000000000000111100 /
b00000000000000000000000000111100 0
#26000000000000000
0#
0'
0*
0.
#26050000000000000
1#
1'
1*
b00000000000000000000000000111101 ,
1.
b00000000000000000000000000111101 /
b00000000000000000000000000111101 0
#26100000000000000
0#
0'
0*
0.
#26150000000000000
1#
1'
1*
b00000000000000000000000000111110 ,
1.
b00000000000000000000000000111110 /
b00000000000000000000000000111110 0
#26200000000000000
0#
0'
0*
0.
#26250000000000000
1#
1'
1*
b00000000000000000000000000111111 ,
1.
b00000000000000000000000000111111 /
b00000000000000000000000000111111 0
#26300000000000000
0#
0'
0*
0.
#26350000000000000
1#
1'
1*
b00000000000000000000000001000000 ,
1.
b00000000000000000000000001000000 /
b00000000000000000000000001000000 0
#26400000000000000
0#
0'
0*
0.
#26450000000000000
1#
1'
1*
b00000000000000000000000001000001 ,
1.
b00000000000000000000000001000001 /
b00000000000000000000000001000001 0
#26500000000000000
0#
0'
0*
0.
#26550000000000000
1#
1'
1*
b00000000000000000000000001000010 ,
1.
b00000000000000000000000001000010 /
b00000000000000000000000001000010 0
#26600000000000000
0#
0'
0*
0.
#26650000000000000
1#
1'
1*
b00000000000000000000000001000011 ,
1.
b00000000000000000000000001000011 /
b00000000000000000000000001000011 0
#26700000000000000
0#
0'
0*
0.
#26750000000000000
1#
1'
1*
b00000000000000000000000001000100 ,
1.
b00000000000000000000000001000100 /
b00000000000000000000000001000100 0
#26800000000000000
0#
0'
0*
0.
#26850000000000000
1#
1'
1*
b00000000000000000000000001000101 ,
1.
b00000000000000000000000001000101 /
b00000000000000000000000001000101 0
#26900000000000000
0#
0'
0*
0.
#26950000000000000
1#
1'
1*
b00000000000000000000000001000110 ,
1.
b00000000000000000000000001000110 /
b00000000000000000000000001000110 0
#27000000000000000
0#
0'
0*
0.
#27050000000000000
1#
1'
1*
b00000000000000000000000001000111 ,
1.
b00000000000000000000000001000111 /
b00000000000000000000000001000111 0
#27100000000000000
0#
0'
0*
0.
#27150000000000000
1#
1'
1*
b00000000000000000000000001001000 ,
1.
b00000000000000000000000001001000 /
b00000000000000000000000001001000 0
#27200000000000000
0#
0'
0*
0.
#27250000000000000
1#
1'
1*
b00000000000000000000000001001001 ,
1.
b00000000000000000000000001001001 /
b00000000000000000000000001001001 0
#27300000000000000
0#
0'
0*
0.
#27350000000000000
1#
1'
1*
b00000000000000000000000001001010 ,
1.
b00000000000000000000000001001010 /
b00000000000000000000000001001010 0
#27400000000000000
0#
0'
0*
0.
#27450000000000000
1#
1'
1*
b00000000000000000000000001001011 ,
1.
b00000000000000000000000001001011 /
b00000000000000000000000001001011 0
#27500000000000000
0#
0'
0*
0.
#27550000000000000
1#
1'
1*
b00000000000000000000000001001100 ,
1.
b00000000000000000000000001001100 /
b00000000000000000000000001001100 0
#27600000000000000
0#
0'
0*
0.
#27650000000000000
1#
1'
1*
b00000000000000000000000001001101 ,
1.
b00000000000000000000000001001101 /
b00000000000000000000000001001101 0
#27700000000000000
0#
0'
0*
0.
#27750000000000000
1#
1'
1*
b00000000000000000000000001001110 ,
1.
b00000000000000000000000001001110 /
b00000000000000000000000001001110 0
#27800000000000000
0#
0'
0*
0.
#27850000000000000
1#
1'
1*
b00000000000000000000000001001111 ,
1.
b00000000000000000000000001001111 /
b00000000000000000000000001001111 0
#27900000000000000
0#
0'
0*
0.
#27950000000000000
1#
1'
1*
b00000000000000000000000001010000 ,
1.
b00000000000000000000000001010000 /
b00000000000000000000000001010000 0
#28000000000000000
0#
0'
0*
0.
#28050000000000000
1#
1'
1*
b00000000000000000000000001010001 ,
1.
b00000000000000000000000001010001 /
b00000000000000000000000001010001 0
#28100000000000000
0#
0'
0*
0.
#28150000000000000
1#
1'
1*
b00000000000000000000000001010010 ,
1.
b00000000000000000000000001010010 /
b00000000000000000000000001010010 0
#28200000000000000
0#
0'
0*
0.
#28250000000000000
1#
1'
1*
b00000000000000000000000001010011 ,
1.
b00000000000000000000000001010011 /
b00000000000000000000000001010011 0
#28300000000000000
0#
0'
0*
0.
#28350000000000000
1#
1'
1*
b00000000000000000000000001010100 ,
1.
b00000000000000000000000001010100 /
b00000000000000000000000001010100 0
#28400000000000000
0#
0'
0*
0.
#28450000000000000
1#
1'
1*
b00000000000000000000000001010101 ,
1.
b00000000000000000000000001010101 /
b00000000000000000000000001010101 0
#28500000000000000
0#
0'
0*
0.
#28550000000000000
1#
1'
1*
b00000000000000000000000001010110 ,
1.
b00000000000000000000000001010110 /
b00000000000000000000000001010110 0
#28600000000000000
0#
0'
0*
0.
#28650000000000000
1#
1'
1*
b00000000000000000000000001010111 ,
1.
b00000000000000000000000001010111 /
b00000000000000000000000001010111 0
#28700000000000000
0#
0'
0*
0.
#28750000000000000
1#
1'
1*
b00000000000000000000000001011000 ,
1.
b00000000000000000000000001011000 /
b00000000000000000000000001011000 0
#28800000000000000
0#
0'
0*
0.
#28850000000000000
1#
1'
1*
b00000000000000000000000001011001 ,
1.
b00000000000000000000000001011001 /
b00000000000000000000000001011001 0
#28900000000000000
0#
0'
0*
0.
