counter/counter.vhd
library ieee;
use ieee.std_logic_1164.all;
use ieee.numeric_std.all;

entity counter is
  generic (
    data_width : integer := 8
  );
  port (
    reset : in std_logic;
    clock : in std_logic;
    count : out std_logic_vector(data_width-1 downto 0)
  );
end entity;
architecture behavioral of counter is
  signal count_reg : unsigned(data_width-1 downto 0) := (others => '0');
begin
  process (clock, reset)
  begin
    if rising_edge(clock) then
      count_reg <= count_reg + 1;
    end if;
    if reset = '1' then
      count_reg <= (others => '0');
    end if;
  end process;
  count <= std_logic_vector(count_reg);
end architecture;

counter/tb.vhd
library ieee;
use ieee.std_logic_1164.all;
use ieee.numeric_std.all;

entity tb is
end tb;

architecture test of tb is
  constant frq : real      := 10.0;
  signal   run : boolean   := true;
  signal   rst : std_logic := '0';
  signal   clk : std_logic := '0';

  component counter is
    generic (
      data_width : integer
    );
    port (
      reset : in std_logic;
      clock : in std_logic;
      count : out std_logic_vector(data_width-1 downto 0)
    );
  end component;

  signal count_output : std_logic_vector(15 downto 0) := (others => '0');
begin
  run <= false after 6000 sec;
  clk <= not clk after (0.5/frq) * 1 sec when run;
  rst <= '1' after 10 sec;

  counter_instance : counter
    generic map (16)
    port map (rst, clk, count_output);
end test;

counter/build/counter.vcd
$date
  Tue Feb 04 21:18:28 2025
$end
$version
  GHDL v0
$end
$timescale
  1 fs
$end
$scope module standard $end
$upscope $end
$scope module std_logic_1164 $end
$upscope $end
$scope module numeric_std $end
$upscope $end
$scope module tb $end
$var reg 1 ! run $end
$var reg 1 " rst $end
$var reg 1 # clk $end
$var reg 16 $ count_output[15:0] $end
$scope module counter_instance $end
$var reg 1 % reset $end
$var reg 1 & clock $end
$var reg 16 ' count[15:0] $end
$var reg 16 ( count_reg[15:0] $end
$upscope $end
$upscope $end
$enddefinitions $end
#0
1!
0"
0#
b0000000000000000 $
0%
0&
b0000000000000000 '
b0000000000000000 (
#50000000000000
1#
b0000000000000001 $
1&
b0000000000000001 '
b0000000000000001 (
#100000000000000
0#
0&
#150000000000000
1#
b0000000000000010 $
1&
b0000000000000010 '
b0000000000000010 (
#200000000000000
0#
0&
#250000000000000
1#
b0000000000000011 $
1&
b0000000000000011 '
b0000000000000011 (
#300000000000000
0#
0&
#350000000000000
1#
b0000000000000100 $
1&
b0000000000000100 '
b0000000000000100 (
#400000000000000
0#
0&
#450000000000000
1#
b0000000000000101 $
1&
b0000000000000101 '
b0000000000000101 (
#500000000000000
0#
0&
#550000000000000
1#
b0000000000000110 $
1&
b0000000000000110 '
b0000000000000110 (
#600000000000000
0#
0&
#650000000000000
1#
b0000000000000111 $
1&
b0000000000000111 '
b0000000000000111 (
#700000000000000
0#
0&
#750000000000000
1#
b0000000000001000 $
1&
b0000000000001000 '
b0000000000001000 (
#800000000000000
0#
0&
#850000000000000
1#
b0000000000001001 $
1&
b0000000000001001 '
b0000000000001001 (
#900000000000000
0#
0&
#950000000000000
1#
b0000000000001010 $
1&
b0000000000001010 '
b0000000000001010 (
#1000000000000000
0#
0&
#1050000000000000
1#
b0000000000001011 $
1&
b0000000000001011 '
b0000000000001011 (
#1100000000000000
0#
0&
#1150000000000000
1#
b0000000000001100 $
1&
b0000000000001100 '
b0000000000001100 (
#1200000000000000
0#
0&
#1250000000000000
1#
b0000000000001101 $
1&
b0000000000001101 '
b0000000000001101 (
#1300000000000000
0#
0&
#1350000000000000
1#
b0000000000001110 $
1&
b0000000000001110 '
b0000000000001110 (
#1400000000000000
0#
0&
#1450000000000000
1#
b0000000000001111 $
1&
b0000000000001111 '
b0000000000001111 (
#1500000000000000
0#
0&
#1550000000000000
1#
b0000000000010000 $
1&
b0000000000010000 '
b0000000000010000 (
#1600000000000000
0#
0&
#1650000000000000
1#
b0000000000010001 $
1&
b0000000000010001 '
b0000000000010001 (
#1700000000000000
0#
0&
#1750000000000000
1#
b0000000000010010 $
1&
b0000000000010010 '
b0000000000010010 (
#1800000000000000
0#
0&
#1850000000000000
1#
b0000000000010011 $
1&
b0000000000010011 '
b0000000000010011 (
#1900000000000000
0#
0&
#1950000000000000
1#
b0000000000010100 $
1&
b0000000000010100 '
b0000000000010100 (
#2000000000000000
0#
0&
#2050000000000000
1#
b0000000000010101 $
1&
b0000000000010101 '
b0000000000010101 (
#2100000000000000
0#
0&
#2150000000000000
1#
b0000000000010110 $
1&
b0000000000010110 '
b0000000000010110 (
#2200000000000000
0#
0&
#2250000000000000
1#
b0000000000010111 $
1&
b0000000000010111 '
b0000000000010111 (
#2300000000000000
0#
0&
#2350000000000000
1#
b0000000000011000 $
1&
b0000000000011000 '
b0000000000011000 (
#2400000000000000
0#
0&
#2450000000000000
1#
b0000000000011001 $
1&
b0000000000011001 '
b0000000000011001 (
#2500000000000000
0#
0&
#2550000000000000
1#
b0000000000011010 $
1&
b0000000000011010 '
b0000000000011010 (
#2600000000000000
0#
0&
#2650000000000000
1#
b0000000000011011 $
1&
b0000000000011011 '
b0000000000011011 (
#2700000000000000
0#
0&
#2750000000000000
1#
b0000000000011100 $
1&
b0000000000011100 '
b0000000000011100 (
#2800000000000000
0#
0&
#2850000000000000
1#
b0000000000011101 $
1&
b0000000000011101 '
b0000000000011101 (
#2900000000000000
0#
0&
#2950000000000000
1#
b0000000000011110 $
1&
b0000000000011110 '
b0000000000011110 (
#3000000000000000
0#
0&
#3050000000000000
1#
b0000000000011111 $
1&
b0000000000011111 '
b0000000000011111 (
#3100000000000000
0#
0&
#3150000000000000
1#
b0000000000100000 $
1&
b0000000000100000 '
b0000000000100000 (
#3200000000000000
0#
0&
#3250000000000000
1#
b0000000000100001 $
1&
b0000000000100001 '
b0000000000100001 (
#3300000000000000
0#
0&
#3350000000000000
1#
b0000000000100010 $
1&
b0000000000100010 '
b0000000000100010 (
#3400000000000000
0#
0&
#3450000000000000
1#
b0000000000100011 $
1&
b0000000000100011 '
b0000000000100011 (
#3500000000000000
0#
0&
#3550000000000000
1#
b0000000000100100 $
1&
b0000000000100100 '
b0000000000100100 (
#3600000000000000
0#
0&
#3650000000000000
1#
b0000000000100101 $
1&
b0000000000100101 '
b0000000000100101 (
#3700000000000000
0#
0&
#3750000000000000
1#
b0000000000100110 $
1&
b0000000000100110 '
b0000000000100110 (
#3800000000000000
0#
0&
#3850000000000000
1#
b0000000000100111 $
1&
b0000000000100111 '
b0000000000100111 (
#3900000000000000
0#
0&
#3950000000000000
1#
b0000000000101000 $
1&
b0000000000101000 '
b0000000000101000 (
#4000000000000000
0#
0&
#4050000000000000
1#
b0000000000101001 $
1&
b0000000000101001 '
b0000000000101001 (
#4100000000000000
0#
0&
#4150000000000000
1#
b0000000000101010 $
1&
b0000000000101010 '
b0000000000101010 (
#4200000000000000
0#
0&
#4250000000000000
1#
b0000000000101011 $
1&
b0000000000101011 '
b0000000000101011 (
#4300000000000000
0#
0&
#4350000000000000
1#
b0000000000101100 $
1&
b0000000000101100 '
b0000000000101100 (
#4400000000000000
0#
0&
#4450000000000000
1#
b0000000000101101 $
1&
b0000000000101101 '
b0000000000101101 (
#4500000000000000
0#
0&
#4550000000000000
1#
b0000000000101110 $
1&
b0000000000101110 '
b0000000000101110 (
#4600000000000000
0#
0&
#4650000000000000
1#
b0000000000101111 $
1&
b0000000000101111 '
b0000000000101111 (
#4700000000000000
0#
0&
#4750000000000000
1#
b0000000000110000 $
1&
b0000000000110000 '
b0000000000110000 (
#4800000000000000
0#
0&
#4850000000000000
1#
b0000000000110001 $
1&
b0000000000110001 '
b0000000000110001 (
#4900000000000000
0#
0&
#4950000000000000
1#
b0000000000110010 $
1&
b0000000000110010 '
b0000000000110010 (
#5000000000000000
0#
0&
#5050000000000000
1#
b0000000000110011 $
1&
b0000000000110011 '
b0000000000110011 (
#5100000000000000
0#
0&
#5150000000000000
1#
b0000000000110100 $
1&
b0000000000110100 '
b0000000000110100 (
#5200000000000000
0#
0&
#5250000000000000
1#
b0000000000110101 $
1&
b0000000000110101 '
b0000000000110101 (
#5300000000000000
0#
0&
#5350000000000000
1#
b0000000000110110 $
1&
b0000000000110110 '
b0000000000110110 (
#5400000000000000
0#
0&
#5450000000000000
1#
b0000000000110111 $
1&
b0000000000110111 '
b0000000000110111 (
#5500000000000000
0#
0&
#5550000000000000
1#
b0000000000111000 $
1&
b0000000000111000 '
b0000000000111000 (
#5600000000000000
0#
0&
#5650000000000000
1#
b0000000000111001 $
1&
b0000000000111001 '
b0000000000111001 (
#5700000000000000
0#
0&
#5750000000000000
1#
b0000000000111010 $
1&
b0000000000111010 '
b0000000000111010 (
#5800000000000000
0#
0&
#5850000000000000
1#
b0000000000111011 $
1&
b0000000000111011 '
b0000000000111011 (
#5900000000000000
0#
0&
#5950000000000000
1#
b0000000000111100 $
1&
b0000000000111100 '
b0000000000111100 (
#6000000000000000
0#
0&
#6050000000000000
1#
b0000000000111101 $
1&
b0000000000111101 '
b0000000000111101 (
#6100000000000000
0#
0&
#6150000000000000
1#
b0000000000111110 $
1&
b0000000000111110 '
b0000000000111110 (
#6200000000000000
0#
0&
#6250000000000000
1#
b0000000000111111 $
1&
b0000000000111111 '
b0000000000111111 (
#6300000000000000
0#
0&
#6350000000000000
1#
b0000000001000000 $
1&
b0000000001000000 '
b0000000001000000 (
#6400000000000000
0#
0&
#6450000000000000
1#
b0000000001000001 $
1&
b0000000001000001 '
b0000000001000001 (
#6500000000000000
0#
0&
#6550000000000000
1#
b0000000001000010 $
1&
b0000000001000010 '
b0000000001000010 (
#6600000000000000
0#
0&
#6650000000000000
1#
b0000000001000011 $
1&
b0000000001000011 '
b0000000001000011 (
#6700000000000000
0#
0&
#6750000000000000
1#
b0000000001000100 $
1&
b0000000001000100 '
b0000000001000100 (
#6800000000000000
0#
0&
#6850000000000000
1#
b0000000001000101 $
1&
b0000000001000101 '
b0000000001000101 (
#6900000000000000
0#
0&
#6950000000000000
1#
b0000000001000110 $
1&
b0000000001000110 '
b0000000001000110 (
#7000000000000000
0#
0&
#7050000000000000
1#
b0000000001000111 $
1&
b0000000001000111 '
b0000000001000111 (
#7100000000000000
0#
0&
#7150000000000000
1#
b0000000001001000 $
1&
b0000000001001000 '
b0000000001001000 (
#7200000000000000
0#
0&
#7250000000000000
1#
b0000000001001001 $
1&
b0000000001001001 '
b0000000001001001 (
#7300000000000000
0#
0&
#7350000000000000
1#
b0000000001001010 $
1&
b0000000001001010 '
b0000000001001010 (
#7400000000000000
0#
0&
#7450000000000000
1#
b0000000001001011 $
1&
b0000000001001011 '
b0000000001001011 (
#7500000000000000
0#
0&
#7550000000000000
1#
b0000000001001100 $
1&
b0000000001001100 '
b0000000001001100 (
#7600000000000000
0#
0&
#7650000000000000
1#
b0000000001001101 $
1&
b0000000001001101 '
b0000000001001101 (
#7700000000000000
0#
0&
#7750000000000000
1#
b0000000001001110 $
1&
b0000000001001110 '
b0000000001001110 (
#7800000000000000
0#
0&
#7850000000000000
1#
b0000000001001111 $
1&
b0000000001001111 '
b0000000001001111 (
#7900000000000000
0#
0&
#7950000000000000
1#
b0000000001010000 $
1&
b0000000001010000 '
b0000000001010000 (
#8000000000000000
0#
0&
#8050000000000000
1#
b0000000001010001 $
1&
b0000000001010001 '
b0000000001010001 (
#8100000000000000
0#
0&
#8150000000000000
1#
b0000000001010010 $
1&
b0000000001010010 '
b0000000001010010 (
#8200000000000000
0#
0&
#8250000000000000
1#
b0000000001010011 $
1&
b0000000001010011 '
b0000000001010011 (
#8300000000000000
0#
0&
#8350000000000000
1#
b0000000001010100 $
1&
b0000000001010100 '
b0000000001010100 (
#8400000000000000
0#
0&
#8450000000000000
1#
b0000000001010101 $
1&
b0000000001010101 '
b0000000001010101 (
#8500000000000000
0#
0&
#8550000000000000
1#
b0000000001010110 $
1&
b0000000001010110 '
b0000000001010110 (
#8600000000000000
0#
0&
#8650000000000000
1#
b0000000001010111 $
1&
b0000000001010111 '
b0000000001010111 (
#8700000000000000
0#
0&
#8750000000000000
1#
b0000000001011000 $
1&
b0000000001011000 '
b0000000001011000 (
#8800000000000000
0#
0&
#8850000000000000
1#
b0000000001011001 $
1&
b0000000001011001 '
b0000000001011001 (
#8900000000000000
0#
0&
#8950000000000000
1#
b0000000001011010 $
1&
b0000000001011010 '
b0000000001011010 (
#9000000000000000
0#
0&
#9050000000000000
1#
b0000000001011011 $
1&
b0000000001011011 '
b0000000001011011 (
#9100000000000000
0#
0&
#9150000000000000
1#
b0000000001011100 $
1&
b0000000001011100 '
b0000000001011100 (
#9200000000000000
0#
0&
#9250000000000000
1#
b0000000001011101 $
1&
b0000000001011101 '
b0000000001011101 (
#9300000000000000
0#
0&
#9350000000000000
1#
b0000000001011110 $
1&
b0000000001011110 '
b0000000001011110 (
#9400000000000000
0#
0&
#9450000000000000
1#
b0000000001011111 $
1&
b0000000001011111 '
b0000000001011111 (
#9500000000000000
0#
0&
#9550000000000000
1#
b0000000001100000 $
1&
b0000000001100000 '
b0000000001100000 (
#9600000000000000
0#
0&
#9650000000000000
1#
b0000000001100001 $
1&
b0000000001100001 '
b0000000001100001 (
#9700000000000000
0#
0&
#9750000000000000
1#
b0000000001100010 $
1&
b0000000001100010 '
b0000000001100010 (
#9800000000000000
0#
0&
#9850000000000000
1#
b0000000001100011 $
1&
b0000000001100011 '
b0000000001100011 (
#9900000000000000
0#
0&
#9950000000000000
1#
b0000000001100100 $
1&
b0000000001100100 '
b0000000001100100 (
#10000000000000000
1"
0#
b0000000000000000 $
1%
0&
b0000000000000000 '
b0000000000000000 (
